{"Np1Q36NDWAun4PHOc5zLtw==":"bolso%20rosado%201-2000x2236.jpg","jX51g/e/TV+LFwWDJ1HKmA==":"louis-vuitton-n%C3%A9ono%C3%A9-648x648.jpg","6FTOtbBlxt0I/X4qDeDfag==":"louis-vuitton-n%C3%A9ono%C3%A9-lona-2000x2000.jpg","dLLjEajXxLx3BMTDJnvWEw==":"louis-vuitton-montaigne-2000x2000.jpg","u0OEAG2dY1aQWwcE9q2HMQ==":"zagliani-670x407.jpg","102sL4+4FwKf5todIIat2w==":"fendi-670x387.jpg","sOm6e5s3aKq5s5X3YxZieg==":"prada-670x432.jpg","GvzRrJ1VfBsaUCkTg/aR2A==":"bolso%20rosado%202-589x659.jpg","RMYDWswyU/YhR3H7PBVHvQ==":"bolso%20rosado%203-648x648.jpg","xaDne6MLsOyWj+FcMzRIyg==":"prada-589x659.jpg","Dh8DJWOrDP2M90+Ir3DVzw==":"bolso%20rosado%201-2000x2000.jpg","CCIl1XBnS7JGIjHNqocdiA==":"salvatore-589x659.jpg","XpNnqj6PAXVKo9S6aRFPOA==":"fendi1-2000x2000.jpg","OGOPljsaIFYvjUAsJvNeOQ==":"logo1-164x73.jpg","meDhZnC6Vi2WfRwqLcV1YA==":"cartera%20primera%20col-525x600.png","P2sFySkGywQWuWwnh4BjzQ==":"cartera%20segunda%20col-720x960.png","uN2+sKw9DKL7fV8t7qCnWQ==":"cartera%20primera%20col-720x960.png","4MzK2DpOfJH5ZoHWVONLbg==":"logo1-128x57.jpg","l9Pl9R2SCSgJ+mAxdPxZsw==":"background1.jpg","JYp/IfNccfvlaadBp0BuQQ==":"duena-mimimi-567x378.png","Ti5tI5DNWhf2EjzYr/eukw==":"show-room-mimimi-567x378.png","TM33R2V0IVGid8WMsBT21w==":"cartera-8-mimimi-589x659.png","EcQK7xxxD1PcPQ3toJDN8g==":"cartera-3-mimimi-567x567.png","CkmXPGkOvtDXU8gFoNoHcg==":"cartera-8-mimimi-659x659.png","7GCmFxUv6n9rX+mYxh8J5Q==":"cartera-4-mimimi-567x567.png"}